velocity/__init__.py
velocity/__main__.py
velocity/_backends.py
velocity/_build.py
velocity/_config.py
velocity/_exceptions.py
velocity/_graph.py
velocity/_print.py
velocity/_tools.py
olcf_velocity-0.3.2.dist-info/LICENSE.txt
olcf_velocity-0.3.2.dist-info/METADATA
olcf_velocity-0.3.2.dist-info/WHEEL
olcf_velocity-0.3.2.dist-info/top_level.txt
olcf_velocity-0.3.2.dist-info/RECORD
