Metadata-Version: 2.2
Name: olcf-velocity
Version: 0.3.2
Summary: A container build manager
Project-URL: Homepage, https://github.com/olcf/velocity
Project-URL: Issues, https://github.com/olcf/velocity/issues
Requires-Python: >=3.10
License-File: LICENSE.txt
Requires-Dist: pyyaml
Requires-Dist: networkx
Requires-Dist: colorama
Requires-Dist: loguru
Requires-Dist: typing_extensions
